auth/__init__.py
auth/auth.py
mpesa/__init__.py
mpesa/api.py
tests/__init__.py
tests/test_account_balance.py
tests/test_async_ussd_push.py
tests/test_auth.py
tests/test_customer_initiated_payment.py
tests/test_my_pay_out.py
tests/test_pay_out.py
tests/test_register.py
mpesa_python-0.1.1.dist-info/METADATA
mpesa_python-0.1.1.dist-info/WHEEL
mpesa_python-0.1.1.dist-info/top_level.txt
mpesa_python-0.1.1.dist-info/RECORD
